<?xml version='1.0' encoding='UTF-8'?>
<!DOCTYPE Identity PUBLIC "sailpoint.dtd" "sailpoint.dtd">
<Identity correlated="true" lastRefresh="1684719928290" name="Michelle.Perez" needsRefresh="true" password="1:ACP:Qav2/hSpZ7cPwpi2T5QGO9PO7CKTRkVKiub2VXGXm6g=">
  <Attributes>
    <Map>
      <entry key="displayName" value="Michelle.Perez"/>
    </Map>
  </Attributes>
  <Links>
    <Link displayName="Michelle.Perez" identity="1a2b3b4a" lastRefresh="1687056813374">
      <ApplicationRef>
        <Reference class="sailpoint.object.Application" name="HR-Employee"/>
      </ApplicationRef>
      <Attributes>
        <Map>
          <entry key="costcenter">
            <value>
              <List>
                <String>R03e</String>
                <String>L09e</String>
              </List>
            </value>
          </entry>
          <entry key="department" value="Human Resources"/>
          <entry key="email" value="Michelle.Perez@demoexample.com"/>
          <entry key="employeeId" value="1a2b3b4a"/>
          <entry key="firstName" value="Michelle"/>
          <entry key="fullName" value="Michelle.Perez"/>
          <entry key="inactiveIdentity" value="FALSE"/>
          <entry key="jobtitle" value="Training &amp; Development Specialist"/>
          <entry key="lastName" value="Perez"/>
          <entry key="location" value="Brazil"/>
          <entry key="managerId" value="1a2b3b"/>
          <entry key="region" value="Americas"/>
        </Map>
      </Attributes>
    </Link>
  </Links>
</Identity>