<?xml version='1.0' encoding='UTF-8'?>
<!DOCTYPE Identity PUBLIC "sailpoint.dtd" "sailpoint.dtd">
<Identity correlated="true" lastRefresh="1684719928027" name="Joseph.Thompson" needsRefresh="true" password="1:ACP:ilhPIbLyRDrFnYfKJd38sqd3N7e+N9i9x2r3dfK8Pb8=">
  <Attributes>
    <Map>
      <entry key="displayName" value="Joseph.Thompson"/>
    </Map>
  </Attributes>
  <Links>
    <Link displayName="Joseph.Thompson" identity="1a2a3a4a" lastRefresh="1687056813374">
      <ApplicationRef>
        <Reference class="sailpoint.object.Application" name="HR-Employee"/>
      </ApplicationRef>
      <Attributes>
        <Map>
          <entry key="costcenter">
            <value>
              <List>
                <String>R03e</String>
                <String>L07e</String>
              </List>
            </value>
          </entry>
          <entry key="department" value="Information Technology"/>
          <entry key="email" value="Joseph.Thompson@demoexample.com"/>
          <entry key="employeeId" value="1a2a3a4a"/>
          <entry key="firstName" value="Joseph"/>
          <entry key="fullName" value="Joseph.Thompson"/>
          <entry key="inactiveIdentity" value="FALSE"/>
          <entry key="jobtitle" value="RACF Security Administrator"/>
          <entry key="lastName" value="Thompson"/>
          <entry key="location" value="Austin"/>
          <entry key="managerId" value="1a2a3a"/>
          <entry key="region" value="Americas"/>
        </Map>
      </Attributes>
    </Link>
  </Links>
</Identity>