<?xml version='1.0' encoding='UTF-8'?>
<!DOCTYPE Identity PUBLIC "sailpoint.dtd" "sailpoint.dtd">
<Identity correlated="true" lastRefresh="1684719925621" name="Rose.Hunter" needsRefresh="true" password="1:ACP:MnQvvdly4NDSHp1ucXu8C3kS7NxZ04aKCPLfyRBYahQ=">
  <Attributes>
    <Map>
      <entry key="displayName" value="Rose.Hunter"/>
    </Map>
  </Attributes>
  <Links>
    <Link displayName="Rose.Hunter" identity="1b2b3d4c" lastRefresh="1687056813374">
      <ApplicationRef>
        <Reference class="sailpoint.object.Application" name="HR-Contractor"/>
      </ApplicationRef>
      <Attributes>
        <Map>
          <entry key="costcenter">
            <value>
              <List>
                <String>R01e</String>
                <String>L02e</String>
              </List>
            </value>
          </entry>
          <entry key="department" value="Inventory"/>
          <entry key="email" value="Rose.Hunter@demoexample.com"/>
          <entry key="employeeId" value="1b2b3d4c"/>
          <entry key="firstName" value="Rose"/>
          <entry key="fullName" value="Rose.Hunter"/>
          <entry key="inactiveIdentity" value="FALSE"/>
          <entry key="lastName" value="Hunter"/>
          <entry key="location" value="Munich"/>
          <entry key="managerId" value="1b2b3d"/>
          <entry key="region" value="Europe"/>
        </Map>
      </Attributes>
    </Link>
  </Links>
</Identity>